toto_pubsub/__init__.py
toto_pubsub/consumer.py
toto_pubsub/publisher.py
toto_pubsub_nicolasances-1.0.0.dist-info/LICENSE
toto_pubsub_nicolasances-1.0.0.dist-info/METADATA
toto_pubsub_nicolasances-1.0.0.dist-info/WHEEL
toto_pubsub_nicolasances-1.0.0.dist-info/top_level.txt
toto_pubsub_nicolasances-1.0.0.dist-info/RECORD
