Metadata-Version: 2.1
Name: toto-pubsub-nicolasances
Version: 1.0.0
Summary: A pubsub library for Toto
Home-page: https://github.com/nicolasances/py-toto-pubsub
Author: nicolasances
Author-email: nicolasances@gmail.com
License: UNKNOWN
Platform: UNKNOWN
Classifier: Programming Language :: Python :: 3
Classifier: License :: OSI Approved :: MIT License
Classifier: Operating System :: OS Independent
Requires-Python: >=3.6
